{"format_version":"2.0_optimized","species":"Lagenorhynchus albirostris","lookup_tables":{"taxonomic":{"0":{"appendix":"II","class":"Mammalia","order":"Cetacea","family":"Delphinidae","genus":"Lagenorhynchus"}},"locations":{"0":"AU","1":"CA","2":"CH","3":"DE","4":"DK","5":"ES","6":"FR","7":"GB","8":"GL","9":"IE","10":"IS","11":"NL","12":"NO","13":"NZ","14":"SE","15":"US"},"categorical":{"term":{"bodies":0,"bones":1,"live":2,"skeletons":3,"skins":4,"skulls":5,"specimens":6},"purpose":{"E":0,"S":1,"Z":2},"source":{"I":0,"U":1,"W":2},"reporter_type":{"E":0,"I":1},"unit":{"Number of specimens":0,"g":1,"kg":2}},"categorical_reverse":{"term":{"0":"bodies","1":"bones","2":"live","3":"skeletons","4":"skins","5":"skulls","6":"specimens"},"purpose":{"0":"E","1":"S","2":"Z"},"source":{"0":"I","1":"U","2":"W"},"reporter_type":{"0":"E","1":"I"},"unit":{"0":"Number of specimens","1":"g","2":"kg"}}},"summary":{"total_records":61,"years":{"range":"1981-2022","unique_years":[1981,1982,1983,1984,1991,1993,1994,1996,2000,2004,2005,2006,2008,2011,2012,2013,2015,2017,2018,2019,2020,2021,2022],"total_years":23},"countries":{"importing_countries":["AU","CA","CH","DE","DK","ES","FR","GB","NZ","SE","US"],"exporting_countries":["CA","DK","FR","GB","GL","IE","IS","NL","NO","US"],"total_importing":11,"total_exporting":10},"terms":{"unique_terms":7,"top_terms":[{"term":"specimens","count":50},{"term":"skulls","count":3},{"term":"bones","count":3},{"term":"bodies","count":2},{"term":"live","count":1}]},"quantities":{"kg":{"total":40.31,"count":10,"average":4.031000000000001,"min":0.02,"max":17.0},"g":{"total":3390.0,"count":16,"average":211.875,"min":5.0,"max":500.0},"Number of specimens":{"total":115.0,"count":5,"average":23.0,"min":1.0,"max":50.0}}},"trade_records":[{"id":"803357591","year":1981,"taxonomic_id":0,"term_id":6,"quantity_raw":"1","quantity_normalized":1.0,"importer_id":15,"exporter_id":6,"purpose_id":1,"reporter_type_id":1,"source_file":"trade_db_1.csv","row_number":301368},{"id":"945067111","year":1982,"taxonomic_id":0,"term_id":6,"quantity_raw":"1","quantity_normalized":1.0,"importer_id":6,"exporter_id":15,"origin_id":6,"purpose_id":1,"reporter_type_id":0,"source_file":"trade_db_1.csv","row_number":301369},{"id":"968707711","year":1983,"taxonomic_id":0,"term_id":2,"quantity_raw":"5","quantity_normalized":5.0,"importer_id":15,"exporter_id":1,"purpose_id":2,"reporter_type_id":0,"source_file":"trade_db_1.csv","row_number":301370},{"id":"884205311","year":1983,"taxonomic_id":0,"term_id":0,"quantity_raw":"1","quantity_normalized":1.0,"importer_id":15,"exporter_id":1,"reporter_type_id":0,"source_file":"trade_db_1.csv","row_number":301371},{"id":"540170751","year":1984,"taxonomic_id":0,"term_id":3,"quantity_raw":"1","quantity_normalized":1.0,"importer_id":4,"exporter_id":4,"purpose_id":1,"reporter_type_id":0,"source_file":"trade_db_1.csv","row_number":301372},{"id":"2656655210","year":2011,"taxonomic_id":0,"term_id":6,"quantity_raw":"0.02","quantity_normalized":0.02,"unit_id":2,"importer_id":15,"exporter_id":7,"purpose_id":1,"source_id":2,"reporter_type_id":1,"source_file":"trade_db_10.csv","row_number":287061},{"id":"7785100610","year":2011,"taxonomic_id":0,"term_id":6,"quantity_raw":"0.02","quantity_normalized":0.02,"unit_id":2,"importer_id":15,"exporter_id":7,"purpose_id":1,"source_id":2,"reporter_type_id":1,"source_file":"trade_db_10.csv","row_number":287062},{"id":"7844411110","year":2011,"taxonomic_id":0,"term_id":6,"quantity_raw":"0.02","quantity_normalized":0.02,"unit_id":2,"importer_id":15,"exporter_id":7,"purpose_id":1,"source_id":2,"reporter_type_id":0,"source_file":"trade_db_10.csv","row_number":287063},{"id":"802643892","year":1991,"taxonomic_id":0,"term_id":5,"quantity_raw":"1","quantity_normalized":1.0,"importer_id":7,"exporter_id":9,"purpose_id":1,"source_id":2,"reporter_type_id":0,"source_file":"trade_db_2.csv","row_number":294011},{"id":"876074462","year":1991,"taxonomic_id":0,"term_id":6,"quantity_raw":"1","quantity_normalized":1.0,"importer_id":15,"exporter_id":11,"purpose_id":1,"source_id":2,"reporter_type_id":1,"source_file":"trade_db_2.csv","row_number":294012},{"id":"783406192","year":1991,"taxonomic_id":0,"term_id":6,"quantity_raw":"10","quantity_normalized":10.0,"importer_id":4,"exporter_id":11,"purpose_id":1,"source_id":2,"reporter_type_id":1,"source_file":"trade_db_2.csv","row_number":294013},{"id":"873229652","year":1993,"taxonomic_id":0,"term_id":6,"quantity_raw":"5","quantity_normalized":5.0,"importer_id":15,"exporter_id":1,"purpose_id":1,"source_id":2,"reporter_type_id":0,"source_file":"trade_db_2.csv","row_number":294014},{"id":"130676222","year":1994,"taxonomic_id":0,"term_id":0,"quantity_raw":"5","quantity_normalized":5.0,"importer_id":15,"exporter_id":1,"purpose_id":1,"source_id":2,"reporter_type_id":0,"source_file":"trade_db_2.csv","row_number":294015},{"id":"348718102","year":1994,"taxonomic_id":0,"term_id":6,"quantity_raw":"8","quantity_normalized":8.0,"importer_id":15,"exporter_id":7,"source_id":2,"reporter_type_id":1,"source_file":"trade_db_2.csv","row_number":294016},{"id":"450308992","year":1994,"taxonomic_id":0,"term_id":6,"quantity_raw":"5","quantity_normalized":5.0,"importer_id":15,"exporter_id":1,"source_id":1,"reporter_type_id":1,"source_file":"trade_db_2.csv","row_number":294017},{"id":"582475962","year":1996,"taxonomic_id":0,"term_id":6,"quantity_raw":"2","quantity_normalized":2.0,"importer_id":7,"exporter_id":9,"source_id":2,"reporter_type_id":0,"source_file":"trade_db_2.csv","row_number":294018},{"id":"4781861630","year":2013,"taxonomic_id":0,"term_id":6,"quantity_raw":"28","quantity_normalized":28.0,"importer_id":4,"exporter_id":12,"purpose_id":1,"source_id":2,"reporter_type_id":0,"source_file":"trade_db_30.csv","row_number":340285},{"id":"9782468931","year":2013,"taxonomic_id":0,"term_id":1,"quantity_raw":"15","quantity_normalized":15.0,"importer_id":3,"exporter_id":10,"purpose_id":0,"source_id":2,"reporter_type_id":0,"source_file":"trade_db_31.csv","row_number":279853},{"id":"1927008031","year":2013,"taxonomic_id":0,"term_id":1,"quantity_raw":"20","quantity_normalized":20.0,"importer_id":2,"exporter_id":10,"purpose_id":0,"source_id":2,"reporter_type_id":0,"source_file":"trade_db_31.csv","row_number":279854},{"id":"7513304531","year":2013,"taxonomic_id":0,"term_id":1,"quantity_raw":"2","quantity_normalized":2.0,"importer_id":3,"exporter_id":10,"purpose_id":0,"source_id":2,"reporter_type_id":0,"source_file":"trade_db_31.csv","row_number":279855},{"id":"8275942931","year":2012,"taxonomic_id":0,"term_id":6,"quantity_raw":"21","quantity_normalized":21.0,"importer_id":4,"exporter_id":10,"purpose_id":1,"source_id":2,"reporter_type_id":0,"source_file":"trade_db_31.csv","row_number":279856},{"id":"4426006934","year":2015,"taxonomic_id":0,"term_id":6,"quantity_raw":"1","quantity_normalized":1.0,"importer_id":15,"exporter_id":4,"origin_id":12,"purpose_id":1,"source_id":2,"reporter_type_id":1,"source_file":"trade_db_34.csv","row_number":322466},{"id":"7991633039","year":2017,"taxonomic_id":0,"term_id":6,"quantity_raw":"4","quantity_normalized":4.0,"importer_id":4,"exporter_id":8,"purpose_id":1,"source_id":2,"reporter_type_id":1,"source_file":"trade_db_39.csv","row_number":299425},{"id":"7721605839","year":2017,"taxonomic_id":0,"term_id":6,"quantity_raw":"300","quantity_normalized":300.0,"unit_id":1,"importer_id":14,"exporter_id":8,"purpose_id":1,"source_id":2,"reporter_type_id":1,"source_file":"trade_db_39.csv","row_number":299426},{"id":"9393825039","year":2017,"taxonomic_id":0,"term_id":6,"quantity_raw":"5","quantity_normalized":5.0,"unit_id":1,"importer_id":14,"exporter_id":8,"purpose_id":1,"source_id":2,"reporter_type_id":1,"source_file":"trade_db_39.csv","row_number":299427},{"id":"272791294","year":2000,"taxonomic_id":0,"term_id":6,"quantity_raw":"10","quantity_normalized":10.0,"importer_id":15,"exporter_id":12,"purpose_id":1,"source_id":2,"reporter_type_id":0,"source_file":"trade_db_4.csv","row_number":252885},{"id":"447068774","year":2000,"taxonomic_id":0,"term_id":6,"quantity_raw":"10","quantity_normalized":10.0,"importer_id":15,"exporter_id":12,"purpose_id":1,"source_id":2,"reporter_type_id":1,"source_file":"trade_db_4.csv","row_number":252886},{"id":"6695858440","year":2017,"taxonomic_id":0,"term_id":6,"quantity_raw":"250","quantity_normalized":250.0,"unit_id":1,"importer_id":15,"exporter_id":4,"origin_id":8,"purpose_id":1,"source_id":2,"reporter_type_id":1,"source_file":"trade_db_40.csv","row_number":280174},{"id":"8929488540","year":2017,"taxonomic_id":0,"term_id":6,"quantity_raw":"3","quantity_normalized":3.0,"unit_id":2,"importer_id":15,"exporter_id":4,"origin_id":8,"purpose_id":1,"source_id":2,"reporter_type_id":1,"source_file":"trade_db_40.csv","row_number":280175},{"id":"7162659940","year":2017,"taxonomic_id":0,"term_id":6,"quantity_raw":"300","quantity_normalized":300.0,"unit_id":1,"importer_id":14,"exporter_id":8,"purpose_id":1,"source_id":2,"reporter_type_id":0,"source_file":"trade_db_40.csv","row_number":280176},{"id":"1059563140","year":2017,"taxonomic_id":0,"term_id":6,"quantity_raw":"300","quantity_normalized":300.0,"unit_id":1,"importer_id":14,"exporter_id":8,"purpose_id":1,"source_id":2,"reporter_type_id":0,"source_file":"trade_db_40.csv","row_number":280177},{"id":"1062752240","year":2017,"taxonomic_id":0,"term_id":6,"quantity_raw":"300","quantity_normalized":300.0,"unit_id":1,"importer_id":15,"exporter_id":8,"purpose_id":1,"source_id":2,"reporter_type_id":0,"source_file":"trade_db_40.csv","row_number":280178},{"id":"1501675140","year":2017,"taxonomic_id":0,"term_id":6,"quantity_raw":"250","quantity_normalized":250.0,"unit_id":1,"importer_id":15,"exporter_id":8,"purpose_id":1,"source_id":2,"reporter_type_id":0,"source_file":"trade_db_40.csv","row_number":280179},{"id":"9842754340","year":2017,"taxonomic_id":0,"term_id":6,"quantity_raw":"120","quantity_normalized":120.0,"unit_id":1,"importer_id":14,"exporter_id":8,"purpose_id":1,"source_id":2,"reporter_type_id":0,"source_file":"trade_db_40.csv","row_number":280180},{"id":"9739997540","year":2017,"taxonomic_id":0,"term_id":6,"quantity_raw":"5","quantity_normalized":5.0,"unit_id":1,"importer_id":14,"exporter_id":8,"purpose_id":1,"source_id":2,"reporter_type_id":0,"source_file":"trade_db_40.csv","row_number":280181},{"id":"8840576440","year":2017,"taxonomic_id":0,"term_id":6,"quantity_raw":"4","quantity_normalized":4.0,"importer_id":4,"exporter_id":8,"purpose_id":1,"source_id":2,"reporter_type_id":0,"source_file":"trade_db_40.csv","row_number":280182},{"id":"9134147840","year":2017,"taxonomic_id":0,"term_id":6,"quantity_raw":"3","quantity_normalized":3.0,"unit_id":2,"importer_id":15,"exporter_id":8,"purpose_id":1,"source_id":2,"reporter_type_id":0,"source_file":"trade_db_40.csv","row_number":280183},{"id":"5759066941","year":2018,"taxonomic_id":0,"term_id":6,"quantity_raw":"0.1","quantity_normalized":0.1,"unit_id":2,"importer_id":4,"exporter_id":8,"purpose_id":1,"source_id":2,"reporter_type_id":1,"source_file":"trade_db_41.csv","row_number":383075},{"id":"4308604541","year":2018,"taxonomic_id":0,"term_id":6,"quantity_raw":"0.1","quantity_normalized":0.1,"unit_id":2,"importer_id":4,"exporter_id":8,"purpose_id":1,"source_id":2,"reporter_type_id":1,"source_file":"trade_db_41.csv","row_number":383076},{"id":"9801874343","year":2018,"taxonomic_id":0,"term_id":6,"quantity_raw":"100","quantity_normalized":100.0,"unit_id":1,"importer_id":4,"exporter_id":8,"purpose_id":1,"source_id":2,"reporter_type_id":0,"source_file":"trade_db_42.csv","row_number":337726},{"id":"6871112843","year":2018,"taxonomic_id":0,"term_id":6,"quantity_raw":"100","quantity_normalized":100.0,"unit_id":1,"importer_id":4,"exporter_id":8,"purpose_id":1,"source_id":2,"reporter_type_id":0,"source_file":"trade_db_42.csv","row_number":337727},{"id":"9572514844","year":2019,"taxonomic_id":0,"term_id":6,"quantity_raw":"0.05","quantity_normalized":0.05,"unit_id":2,"importer_id":5,"exporter_id":10,"purpose_id":1,"source_id":2,"reporter_type_id":1,"source_file":"trade_db_43.csv","row_number":287100},{"id":"2641669545","year":2019,"taxonomic_id":0,"term_id":6,"quantity_raw":"140","quantity_normalized":140.0,"unit_id":1,"importer_id":1,"exporter_id":8,"purpose_id":1,"source_id":2,"reporter_type_id":0,"source_file":"trade_db_45.csv","row_number":250540},{"id":"3841841047","year":2020,"taxonomic_id":0,"term_id":6,"quantity_raw":"400","quantity_normalized":400.0,"unit_id":1,"importer_id":14,"exporter_id":8,"purpose_id":1,"source_id":2,"reporter_type_id":0,"source_file":"trade_db_47.csv","row_number":318785},{"id":"3910677148","year":2018,"taxonomic_id":0,"term_id":6,"quantity_raw":"3","quantity_normalized":3.0,"importer_id":15,"exporter_id":7,"purpose_id":1,"source_id":2,"reporter_type_id":1,"source_file":"trade_db_48.csv","row_number":236582},{"id":"7607995249","year":2021,"taxonomic_id":0,"term_id":6,"quantity_raw":"17","quantity_normalized":17.0,"unit_id":2,"importer_id":4,"exporter_id":8,"purpose_id":1,"source_id":2,"reporter_type_id":1,"source_file":"trade_db_49.csv","row_number":310731},{"id":"5393471249","year":2019,"taxonomic_id":0,"term_id":6,"quantity_raw":"250","quantity_normalized":250.0,"unit_id":1,"importer_id":1,"exporter_id":15,"origin_id":8,"purpose_id":1,"source_id":2,"reporter_type_id":0,"source_file":"trade_db_49.csv","row_number":310732},{"id":"8689014950","year":2021,"taxonomic_id":0,"term_id":6,"quantity_raw":"17","quantity_normalized":17.0,"unit_id":2,"importer_id":4,"exporter_id":8,"purpose_id":1,"source_id":2,"reporter_type_id":0,"source_file":"trade_db_50.csv","row_number":337304},{"id":"2287273450","year":2021,"taxonomic_id":0,"term_id":5,"quantity_raw":"1","quantity_normalized":1.0,"unit_id":0,"importer_id":14,"exporter_id":8,"purpose_id":1,"source_id":2,"reporter_type_id":0,"source_file":"trade_db_50.csv","row_number":337305},{"id":"7384416451","year":2022,"taxonomic_id":0,"term_id":6,"quantity_raw":"500","quantity_normalized":500.0,"unit_id":1,"importer_id":1,"exporter_id":4,"origin_id":8,"purpose_id":1,"source_id":2,"reporter_type_id":0,"source_file":"trade_db_51.csv","row_number":249739},{"id":"7372306552","year":2022,"taxonomic_id":0,"term_id":6,"quantity_raw":"70","quantity_normalized":70.0,"unit_id":1,"importer_id":14,"exporter_id":8,"purpose_id":1,"source_id":2,"reporter_type_id":0,"source_file":"trade_db_52.csv","row_number":344876},{"id":"7250762852","year":2022,"taxonomic_id":0,"term_id":5,"quantity_raw":"1","quantity_normalized":1.0,"unit_id":0,"importer_id":14,"exporter_id":8,"purpose_id":1,"source_id":2,"reporter_type_id":0,"source_file":"trade_db_52.csv","row_number":344877},{"id":"2389000453","year":2022,"taxonomic_id":0,"term_id":4,"quantity_raw":"13","quantity_normalized":13.0,"unit_id":0,"importer_id":15,"exporter_id":1,"origin_id":6,"purpose_id":0,"source_id":0,"reporter_type_id":1,"source_file":"trade_db_53.csv","row_number":323521},{"id":"7843510053","year":2020,"taxonomic_id":0,"term_id":6,"quantity_raw":"50","quantity_normalized":50.0,"unit_id":0,"importer_id":15,"exporter_id":1,"purpose_id":1,"source_id":2,"reporter_type_id":0,"source_file":"trade_db_53.csv","row_number":323522},{"id":"1281594554","year":2022,"taxonomic_id":0,"term_id":6,"quantity_raw":"50","quantity_normalized":50.0,"unit_id":0,"importer_id":15,"exporter_id":1,"purpose_id":1,"source_id":2,"reporter_type_id":0,"source_file":"trade_db_54.csv","row_number":173746},{"id":"639245066","year":2004,"taxonomic_id":0,"term_id":6,"quantity_raw":"44","quantity_normalized":44.0,"importer_id":7,"exporter_id":12,"purpose_id":1,"source_id":2,"reporter_type_id":0,"source_file":"trade_db_6.csv","row_number":253460},{"id":"217795346","year":2005,"taxonomic_id":0,"term_id":6,"quantity_raw":"1","quantity_normalized":1.0,"importer_id":13,"exporter_id":15,"purpose_id":1,"source_id":2,"reporter_type_id":0,"source_file":"trade_db_6.csv","row_number":253461},{"id":"747168227","year":2006,"taxonomic_id":0,"term_id":6,"quantity_raw":"1","quantity_normalized":1.0,"importer_id":0,"exporter_id":1,"purpose_id":1,"source_id":2,"reporter_type_id":0,"source_file":"trade_db_7.csv","row_number":268246},{"id":"389031497","year":2006,"taxonomic_id":0,"term_id":6,"quantity_raw":"11","quantity_normalized":11.0,"importer_id":7,"exporter_id":15,"purpose_id":1,"source_id":2,"reporter_type_id":0,"source_file":"trade_db_7.csv","row_number":268247},{"id":"187395297","year":2006,"taxonomic_id":0,"term_id":6,"quantity_raw":"1","quantity_normalized":1.0,"importer_id":0,"exporter_id":1,"purpose_id":1,"source_id":2,"reporter_type_id":1,"source_file":"trade_db_7.csv","row_number":268248},{"id":"610155308","year":2008,"taxonomic_id":0,"term_id":6,"quantity_raw":"10","quantity_normalized":10.0,"importer_id":4,"exporter_id":10,"purpose_id":1,"source_id":2,"reporter_type_id":0,"source_file":"trade_db_8.csv","row_number":285961}],"metadata":{"optimization_date":"2025-05-24T19:38:41.355113","original_records":61,"optimized_records":61,"original_extraction":{"extraction_date":"2025-05-24T19:36:18.821546","total_records":61,"source_files":["trade_db_10.csv","trade_db_6.csv","trade_db_41.csv","trade_db_49.csv","trade_db_50.csv","trade_db_31.csv","trade_db_8.csv","trade_db_43.csv","trade_db_53.csv","trade_db_2.csv","trade_db_51.csv","trade_db_7.csv","trade_db_48.csv","trade_db_42.csv","trade_db_45.csv","trade_db_30.csv","trade_db_34.csv","trade_db_40.csv","trade_db_47.csv","trade_db_1.csv","trade_db_39.csv","trade_db_54.csv","trade_db_52.csv","trade_db_4.csv"],"date_range":{"earliest_year":1981,"latest_year":2022}},"compression_info":{"taxonomic_combinations":1,"unique_locations":16,"categorical_mappings":{"term":7,"purpose":3,"source":3,"reporter_type":2,"unit":3}}}}